odoo10_addon_website_sale_line_total-10.0.1.0.0-py2.7-nspkg.pth
odoo10_addon_website_sale_line_total-10.0.1.0.0.dist-info/top_level.txt
odoo10_addon_website_sale_line_total-10.0.1.0.0.dist-info/WHEEL
odoo10_addon_website_sale_line_total-10.0.1.0.0.dist-info/RECORD
odoo10_addon_website_sale_line_total-10.0.1.0.0.dist-info/metadata.json
odoo10_addon_website_sale_line_total-10.0.1.0.0.dist-info/DESCRIPTION.rst
odoo10_addon_website_sale_line_total-10.0.1.0.0.dist-info/METADATA
odoo10_addon_website_sale_line_total-10.0.1.0.0.dist-info/namespace_packages.txt
odoo/addons/website_sale_line_total/__manifest__.py
odoo/addons/website_sale_line_total/__init__.py
odoo/addons/website_sale_line_total/README.rst
odoo/addons/website_sale_line_total/views/website_sale_line_total_view.xml
odoo/addons/website_sale_line_total/static/description/icon.png
