Metadata-Version: 2.0
Name: odoo10-addon-website-sale-line-total
Version: 10.0.1.0.0
Summary: Adds separate columns for unit price and total price
Home-page: https://www.github.com/OCA/website
Author: SMDrugstore, Odoo Community Association (OCA)
Author-email: support@odoo-community.org
License: LGPL-3
Platform: UNKNOWN
Requires-Dist: odoo (<10.1dev,>=10.0)
Classifier: Programming Language :: Python :: 2.7
Classifier: Framework :: Odoo
Classifier: License :: OSI Approved :: GNU Lesser General Public License v3 (LGPLv3)
